mannaqrng.py
mannaqrng-1.dist-info/METADATA
mannaqrng-1.dist-info/WHEEL
mannaqrng-1.dist-info/top_level.txt
mannaqrng-1.dist-info/RECORD
